payfacMPSdk/__init__.py
payfacMPSdk/communication.py
payfacMPSdk/generatedClass.py
payfacMPSdk/payfac_agreement.py
payfacMPSdk/payfac_legalEntity.py
payfacMPSdk/payfac_mcc.py
payfacMPSdk/payfac_principal.py
payfacMPSdk/payfac_submerchant.py
payfacMPSdk/utils.py
payfacMPSdk/version.py
payfacMPSdk/schema/merchant-onboard-api-v15.xsd
payfacmpsdk-15.0.0.dist-info/licenses/LICENSE
scripts/__init__.py
scripts/payfac_mp_sdk_setup.py
payfacmpsdk-15.0.0.dist-info/METADATA
payfacmpsdk-15.0.0.dist-info/WHEEL
payfacmpsdk-15.0.0.dist-info/entry_points.txt
payfacmpsdk-15.0.0.dist-info/top_level.txt
payfacmpsdk-15.0.0.dist-info/RECORD
