Metadata-Version: 2.4
Name: payfacmpsdk
Version: 15.0.0
Summary: Worldpay payfac SDK
Home-page: https://developer.vantiv.com/community/ecommerce
Author: Worldpay
Author-email: SDKSupport@vantiv.com
License: MIT
Classifier: Development Status :: 5 - Production/Stable
Classifier: Intended Audience :: Developers
Classifier: Intended Audience :: System Administrators
Classifier: Intended Audience :: Information Technology
Classifier: License :: OSI Approved :: MIT License
Classifier: Operating System :: OS Independent
Classifier: Programming Language :: Python
Classifier: Programming Language :: Python :: 2
Classifier: Programming Language :: Python :: 2.7
Classifier: Programming Language :: Python :: 3
Classifier: Programming Language :: Python :: 3.4
Classifier: Programming Language :: Python :: 3.5
Classifier: Programming Language :: Python :: 3.6
Classifier: Topic :: Office/Business :: Financial
Classifier: Topic :: Software Development :: Libraries
Classifier: Topic :: Software Development :: Libraries :: Python Modules
License-File: LICENSE
Requires-Dist: paramiko>=1.14.0
Requires-Dist: requests>=2.21.0
Requires-Dist: six>=1.10.0
Requires-Dist: xmlschema<=1.0.18,>=1.0.3
Requires-Dist: generateDS>=2.29.24
Requires-Dist: unittest2>=1.1.0
Requires-Dist: python-dateutil>=2.7.3
Requires-Dist: setuptools
Requires-Dist: mock
Requires-Dist: lxml
Requires-Dist: wheel
Dynamic: author
Dynamic: author-email
Dynamic: classifier
Dynamic: description
Dynamic: description-content-type
Dynamic: home-page
Dynamic: license
Dynamic: license-file
Dynamic: requires-dist
Dynamic: summary
